{
  "timestamp": "2026-06-01T19:13:18.727063",
  "trading_mode": false,
  "balances": {
    "XAUt0": 0.050067,
    "PAXG": 0.00516051,
    "GOLD": 0.0,
    "SOL": 0.060889925
  },
  "total_gold_balance": 0.05522751,
  "best_opportunity": {
    "pair_id": "XAUt0_GOLD_buy",
    "from": "GOLD",
    "to": "XAUt0",
    "direction": "buy",
    "label": "XAUt0 ↔ GOLD",
    "quote": {
      "inputMint": "GoLDppdjB1vDTPSGxyMJFqdnj134yH6Prg9eqsGDiw6A",
      "inAmount": "25000",
      "outputMint": "AymATz4TCL9sWNEEV9Kvyz45CHVhDZ6kUgjTJPzLpU9P",
      "outAmount": "25026",
      "otherAmountThreshold": "24901",
      "swapMode": "ExactIn",
      "slippageBps": 50,
      "platformFee": null,
      "priceImpactPct": "0.00252718040089086859688196",
      "routePlan": [
        {
          "swapInfo": {
            "ammKey": "CmQFZMT6MtFMSPaw82uGYGp7jJpX6YJZMAjKW3mRpMmk",
            "label": "ZeroFi",
            "inputMint": "GoLDppdjB1vDTPSGxyMJFqdnj134yH6Prg9eqsGDiw6A",
            "outputMint": "EPjFWdd5AufqSSqeM2qN1xzybapC8G4wEGGkZwyTDt1v",
            "inAmount": "25000",
            "outAmount": "111627163",
            "updateContextSlot": "423634969"
          },
          "percent": 100,
          "bps": null
        },
        {
          "swapInfo": {
            "ammKey": "CHrziAKSF7DZ248Kz1j9YFRtYsMmPQNwPQiumKJxnNgn",
            "label": "Meteora DLMM",
            "inputMint": "EPjFWdd5AufqSSqeM2qN1xzybapC8G4wEGGkZwyTDt1v",
            "outputMint": "AymATz4TCL9sWNEEV9Kvyz45CHVhDZ6kUgjTJPzLpU9P",
            "inAmount": "111627163",
            "outAmount": "25026",
            "updateContextSlot": "423634969"
          },
          "percent": 100,
          "bps": null
        }
      ],
      "contextSlot": 423634970,
      "timeTaken": 0.00086473,
      "swapUsdValue": "111.75681716584711667411712114",
      "mostReliableAmmsQuoteReport": {
        "info": {
          "BZtgQEyS6eXUXicYPHecYQ7PybqodXQMvkjUbP4R8mUU": "111725492",
          "3Vj8miZuTSdonf4W1xLdYFatrXLm38CShrCi7NbZS5Ah": "111134394",
          "9KWAAyaYF7nmMWzirnBmVhE1q4YXPHcXjzfi6YreNtDY": "25009"
        }
      },
      "longtailMarketQuoteReport": null,
      "useIncurredSlippageForQuoting": null,
      "useRewards": null,
      "otherRoutePlans": null,
      "loadedLongtailToken": false,
      "instructionVersion": null
    },
    "price": 1.00104,
    "profit_pct": 0.10399999999999299,
    "in_ui": 0.025,
    "out_ui": 0.025026,
    "in_raw": 25000,
    "is_actionable": false,
    "from_mint": "GoLDppdjB1vDTPSGxyMJFqdnj134yH6Prg9eqsGDiw6A",
    "to_mint": "AymATz4TCL9sWNEEV9Kvyz45CHVhDZ6kUgjTJPzLpU9P",
    "from_dec": 6,
    "to_dec": 6
  },
  "best_actionable": null,
  "config": {
    "threshold_pct": 0.6000000000000005,
    "fraction_size": 0.025,
    "total_amount": 0.05,
    "min_sol": 0.01,
    "auto_buy_sol": true
  },
  "stats": {
    "total_swaps": 0,
    "last_swap": null
  },
  "_synced_at": "2026-06-01T19:13:45.619373",
  "_sync_source": "github_sync.py"
}